mosip_auth_sdk/__init__.py
mosip_auth_sdk/_authenticator/__init__.py
mosip_auth_sdk/_authenticator/auth_models.py
mosip_auth_sdk/_authenticator/authenticator-config.toml
mosip_auth_sdk/_authenticator/authenticator.py
mosip_auth_sdk/_authenticator/exceptions/__init__.py
mosip_auth_sdk/_authenticator/exceptions/authenticator_exception.py
mosip_auth_sdk/_authenticator/utils/__init__.py
mosip_auth_sdk/_authenticator/utils/cryptoutil.py
mosip_auth_sdk/_authenticator/utils/restutil.py
mosip_auth_sdk/models/__init__.py
mosip_auth_sdk-0.5.3.dist-info/LICENSE
mosip_auth_sdk-0.5.3.dist-info/METADATA
mosip_auth_sdk-0.5.3.dist-info/WHEEL
mosip_auth_sdk-0.5.3.dist-info/RECORD
