Metadata-Version: 2.1
Name: mosip-auth-sdk
Version: 0.5.3
Summary: Simplified SDK for MOSIP Authentication
License: Mozilla Public License Version 2.0
Author: Abdul Bathish
Requires-Python: >=3.10,<4.0
Classifier: License :: Other/Proprietary License
Classifier: Programming Language :: Python :: 3
Classifier: Programming Language :: Python :: 3.10
Classifier: Programming Language :: Python :: 3.11
Classifier: Programming Language :: Python :: 3.12
Classifier: Programming Language :: Python :: 3.13
Requires-Dist: cryptography (>=43.0.3,<44.0.0)
Requires-Dist: jwcrypto (>=1.5.6,<2.0.0)
Requires-Dist: pydantic (>=2.9.2,<3.0.0)
Requires-Dist: requests (>=2.32.3,<3.0.0)
